resonant_utils/__init__.py
resonant_utils/admin.py
resonant_utils/allauth.py
resonant_utils/apps.py
resonant_utils/db.py
resonant_utils/files.py
resonant_utils/management.py
resonant_utils/middleware.py
resonant_utils/py.typed
resonant_utils/rest_framework.py
resonant_utils/storages.py
resonant_utils/templatetags/__init__.py
resonant_utils/templatetags/resonant_utils.py
django_resonant_utils-0.16.2.dist-info/METADATA
django_resonant_utils-0.16.2.dist-info/WHEEL
django_resonant_utils-0.16.2.dist-info/licenses/LICENSE
django_resonant_utils-0.16.2.dist-info/licenses/NOTICE
django_resonant_utils-0.16.2.dist-info/RECORD
