Metadata-Version: 2.4
Name: django-resonant-utils
Version: 0.16.2
Summary: Django utilities for data management applications.
Project-URL: Repository, https://github.com/kitware-resonant/django-resonant-utils
Project-URL: Bug Reports, https://github.com/kitware-resonant/django-resonant-utils/issues
Maintainer-email: "Kitware, Inc." <kitware@kitware.com>
License-Expression: Apache-2.0
License-File: LICENSE
License-File: NOTICE
Keywords: django,kitware-resonant,resonant
Classifier: Development Status :: 3 - Alpha
Classifier: Environment :: Web Environment
Classifier: Framework :: Django
Classifier: Framework :: Django :: 5
Classifier: Framework :: Django :: 5.2
Classifier: Intended Audience :: Developers
Classifier: Operating System :: OS Independent
Classifier: Programming Language :: Python
Classifier: Programming Language :: Python :: 3
Classifier: Programming Language :: Python :: 3.10
Classifier: Programming Language :: Python :: 3.11
Classifier: Programming Language :: Python :: 3.12
Classifier: Programming Language :: Python :: 3.13
Classifier: Programming Language :: Python :: 3.14
Requires-Python: >=3.10
Requires-Dist: django>=4.2
Provides-Extra: allauth
Requires-Dist: django-allauth; extra == 'allauth'
Provides-Extra: minio-storage
Requires-Dist: django-minio-storage; extra == 'minio-storage'
Provides-Extra: rest-framework
Requires-Dist: djangorestframework; extra == 'rest-framework'
Provides-Extra: s3-storage
Requires-Dist: django-storages[s3]>=1.14; extra == 's3-storage'
